{"updated":"2026-03-24T06:18:11.500182+00:00","count":94,"quotes":{"ACMESOLAR":{"sym":"ACMESOLAR","name":"ACME SOLAR HOLDINGS LTD","sector":"Utilities","ltp":239.0,"change":1.45,"changePct":0.61,"open":246.0,"high":246.0,"low":237.39,"prev":237.55,"vol":742175,"avgVol":1091568,"mktCap":144827252736,"pe":29.76,"fwdPe":23.2,"pb":3.03,"eps":8.03,"bv":78.98,"roe":null,"divYield":8.0,"w52h":324.3,"w52l":172.63,"ma50":226.88,"ma200":256.02,"beta":null,"opm":65.28,"npm":24.61},"AFCONS":{"sym":"AFCONS","name":"AFCONS INFRASTRUCTURE LTD","sector":"Industrials","ltp":275.1,"change":3.9,"changePct":1.438,"open":274.95,"high":275.7,"low":270.0,"prev":271.2,"vol":131799,"avgVol":519799,"mktCap":101177556992,"pe":22.49,"fwdPe":16.67,"pb":1.89,"eps":12.23,"bv":145.7,"roe":null,"divYield":92.0,"w52h":498.7,"w52l":270.0,"ma50":318.14,"ma200":396.95,"beta":null,"opm":10.65,"npm":3.59},"AZAD":{"sym":"AZAD","name":"AZAD ENGINEERING LIMITED","sector":"Industrials","ltp":1385.3,"change":18.8,"changePct":1.376,"open":1410.5,"high":1413.3,"low":1370.1,"prev":1366.5,"vol":87967,"avgVol":169532,"mktCap":89465094144,"pe":72.42,"fwdPe":51.47,"pb":6.07,"eps":19.13,"bv":228.13,"roe":null,"divYield":null,"w52h":1899.0,"w52l":1159.45,"ma50":1565.14,"ma200":1602.31,"beta":-0.73,"opm":30.23,"npm":21.49},"ABCAPITAL":{"sym":"ABCAPITAL","name":"Aditya Birla Capital Limited","sector":"Financial Services","ltp":298.55,"change":3.6,"changePct":1.221,"open":301.65,"high":303.8,"low":296.2,"prev":294.95,"vol":1781777,"avgVol":6907383,"mktCap":782083358720,"pe":22.5,"fwdPe":14.78,"pb":2.43,"eps":13.27,"bv":123.04,"roe":null,"divYield":null,"w52h":369.3,"w52l":169.43,"ma50":340.64,"ma200":313.41,"beta":0.54,"opm":15.16,"npm":11.07},"ABFRL":{"sym":"ABFRL","name":"Aditya Birla Fashion and Retail Limited","sector":"Consumer Cyclical","ltp":57.75,"change":0.81,"changePct":1.423,"open":58.85,"high":59.1,"low":57.3,"prev":56.94,"vol":2973916,"avgVol":7381850,"mktCap":70258548736,"pe":null,"fwdPe":9.32,"pb":1.12,"eps":-6.98,"bv":51.53,"roe":null,"divYield":null,"w52h":295.7,"w52l":56.52,"ma50":66.49,"ma200":76.2,"beta":-0.46,"opm":8.88,"npm":-3.65},"APOLLOHOSP":{"sym":"APOLLOHOSP","name":"Apollo Hospitals Enterprise Limited","sector":"Healthcare","ltp":7385.0,"change":240.0,"changePct":3.359,"open":7210.0,"high":7398.5,"low":7199.0,"prev":7145.0,"vol":282685,"avgVol":432992,"mktCap":1061849661440,"pe":59.06,"fwdPe":44.32,"pb":11.68,"eps":125.04,"bv":632.45,"roe":null,"divYield":28.0,"w52h":8099.5,"w52l":6430.25,"ma50":7365.26,"ma200":7445.25,"beta":0.13,"opm":11.52,"npm":7.44},"ARROWGREEN":{"sym":"ARROWGREEN","name":"Arrow Greentech Limited","sector":"Consumer Cyclical","ltp":365.4,"change":3.1,"changePct":0.856,"open":375.3,"high":383.8,"low":358.05,"prev":362.3,"vol":11521,"avgVol":28244,"mktCap":5513132544,"pe":10.73,"fwdPe":null,"pb":2.61,"eps":34.06,"bv":140.14,"roe":null,"divYield":110.0,"w52h":817.95,"w52l":341.95,"ma50":422.05,"ma200":549.58,"beta":-0.18,"opm":30.81,"npm":23.79},"ASHOKA":{"sym":"ASHOKA","name":"Ashoka Buildcon Limited","sector":"Industrials","ltp":108.85,"change":2.55,"changePct":2.399,"open":110.0,"high":110.58,"low":107.59,"prev":106.3,"vol":661192,"avgVol":1045784,"mktCap":30573045760,"pe":1.08,"fwdPe":9.4,"pb":0.73,"eps":101.14,"bv":149.95,"roe":null,"divYield":null,"w52h":230.8,"w52l":107.59,"ma50":139.51,"ma200":176.29,"beta":0.14,"opm":21.54,"npm":34.37},"ASALCBR":{"sym":"ASALCBR","name":"Associated Alcohols & Breweries Limited","sector":"Consumer Defensive","ltp":721.0,"change":3.05,"changePct":0.425,"open":723.1,"high":731.0,"low":713.2,"prev":717.95,"vol":15997,"avgVol":47037,"mktCap":14477103104,"pe":15.97,"fwdPe":14.25,"pb":2.24,"eps":45.16,"bv":322.32,"roe":null,"divYield":28.0,"w52h":1477.95,"w52l":696.0,"ma50":813.59,"ma200":978.3,"beta":-0.01,"opm":13.39,"npm":8.53},"AVANTIFEED":{"sym":"AVANTIFEED","name":"Avanti Feeds Limited","sector":"Consumer Defensive","ltp":1121.5,"change":6.5,"changePct":0.583,"open":1150.0,"high":1159.8,"low":1113.7,"prev":1115.0,"vol":150340,"avgVol":1584032,"mktCap":152799477760,"pe":19.88,"fwdPe":22.93,"pb":5.08,"eps":56.42,"bv":220.94,"roe":null,"divYield":81.0,"w52h":1489.0,"w52l":601.55,"ma50":1092.74,"ma200":821.04,"beta":-0.08,"opm":11.58,"npm":10.57},"BBOX":{"sym":"BBOX","name":"Black Box Limited","sector":"Technology","ltp":492.15,"change":13.5,"changePct":2.82,"open":495.0,"high":495.55,"low":486.1,"prev":478.65,"vol":169726,"avgVol":420464,"mktCap":87123877888,"pe":39.4,"fwdPe":25.05,"pb":9.25,"eps":12.49,"bv":53.22,"roe":null,"divYield":21.0,"w52h":613.8,"w52l":320.85,"ma50":517.35,"ma200":517.6,"beta":-0.03,"opm":7.32,"npm":3.45},"MAHABANK":{"sym":"MAHABANK","name":"Bank of Maharashtra","sector":"Financial Services","ltp":63.08,"change":0.76,"changePct":1.22,"open":64.9,"high":64.9,"low":62.42,"prev":62.32,"vol":13550852,"avgVol":23140578,"mktCap":485183291392,"pe":7.49,"fwdPe":null,"pb":1.45,"eps":8.42,"bv":43.45,"roe":21.17,"divYield":401.0,"w52h":77.0,"w52l":42.0,"ma50":66.75,"ma200":59.39,"beta":0.6,"opm":55.35,"npm":49.32},"BDL":{"sym":"BDL","name":"Bharat Dynamics Limited","sector":"Industrials","ltp":1168.0,"change":9.5,"changePct":0.82,"open":1185.1,"high":1194.1,"low":1153.0,"prev":1158.5,"vol":634995,"avgVol":1873475,"mktCap":428144984064,"pe":73.6,"fwdPe":39.93,"pb":10.15,"eps":15.87,"bv":115.06,"roe":null,"divYield":44.0,"w52h":2096.6,"w52l":1141.2,"ma50":1347.68,"ma200":1520.82,"beta":0.01,"opm":1.18,"npm":15.51},"BIOCON":{"sym":"BIOCON","name":"Biocon Limited","sector":"Healthcare","ltp":370.1,"change":2.95,"changePct":0.803,"open":374.0,"high":377.2,"low":368.25,"prev":367.15,"vol":877612,"avgVol":3233234,"mktCap":599314530304,"pe":75.84,"fwdPe":40.1,"pb":1.78,"eps":4.88,"bv":207.92,"roe":null,"divYield":14.0,"w52h":424.95,"w52l":299.0,"ma50":378.38,"ma200":374.93,"beta":0.21,"opm":7.62,"npm":3.59},"MAPMYINDIA":{"sym":"MAPMYINDIA","name":"C. E. Info Systems Limited","sector":"Technology","ltp":858.3,"change":-2.7,"changePct":-0.314,"open":877.7,"high":877.7,"low":850.0,"prev":861.0,"vol":71051,"avgVol":163530,"mktCap":46967603200,"pe":35.73,"fwdPe":23.33,"pb":5.75,"eps":24.02,"bv":149.39,"roe":null,"divYield":41.0,"w52h":2166.7,"w52l":850.0,"ma50":1174.89,"ma200":1588.96,"beta":-0.18,"opm":20.36,"npm":27.92},"CDSL":{"sym":"CDSL","name":"Central Depository Services (India) Limited","sector":"Financial Services","ltp":1172.0,"change":38.2,"changePct":3.369,"open":1170.0,"high":1177.0,"low":1151.1,"prev":1133.8,"vol":1176810,"avgVol":1815135,"mktCap":244947992576,"pe":51.43,"fwdPe":39.59,"pb":14.06,"eps":22.79,"bv":83.38,"roe":null,"divYield":110.0,"w52h":1828.9,"w52l":1079.9,"ma50":1305.96,"ma200":1510.58,"beta":0.1,"opm":51.92,"npm":38.89},"COCHINSHIP":{"sym":"COCHINSHIP","name":"Cochin Shipyard Limited","sector":"Industrials","ltp":1292.0,"change":22.8,"changePct":1.796,"open":1319.0,"high":1321.9,"low":1283.2,"prev":1269.2,"vol":546731,"avgVol":958548,"mktCap":339994771456,"pe":46.69,"fwdPe":39.69,"pb":5.96,"eps":27.67,"bv":216.71,"roe":null,"divYield":104.0,"w52h":2545.0,"w52l":1224.55,"ma50":1486.65,"ma200":1701.45,"beta":0.17,"opm":11.38,"npm":13.73},"COFORGE":{"sym":"COFORGE","name":"Coforge Limited","sector":"Technology","ltp":1108.4,"change":8.0,"changePct":0.727,"open":1127.0,"high":1127.9,"low":1083.0,"prev":1100.4,"vol":978665,"avgVol":3270729,"mktCap":372321255424,"pe":33.14,"fwdPe":20.14,"pb":5.39,"eps":33.45,"bv":205.67,"roe":null,"divYield":145.0,"w52h":1994.0,"w52l":1008.1,"ma50":1411.69,"ma200":1680.62,"beta":0.06,"opm":13.36,"npm":7.89},"DATAPATTNS":{"sym":"DATAPATTNS","name":"Data Patterns (India) Limited","sector":"Industrials","ltp":3193.0,"change":120.4,"changePct":3.919,"open":3134.0,"high":3195.0,"low":3101.9,"prev":3072.6,"vol":354168,"avgVol":894845,"mktCap":178756812800,"pe":72.16,"fwdPe":50.65,"pb":11.62,"eps":44.25,"bv":274.8,"roe":null,"divYield":26.0,"w52h":3609.5,"w52l":1392.25,"ma50":2862.72,"ma200":2765.95,"beta":0.3,"opm":43.13,"npm":25.31},"DATAMATICS":{"sym":"DATAMATICS","name":"Datamatics Global Services Limited","sector":"Technology","ltp":685.9,"change":16.2,"changePct":2.419,"open":685.0,"high":689.6,"low":665.65,"prev":669.7,"vol":34598,"avgVol":259779,"mktCap":40541073408,"pe":20.82,"fwdPe":15.66,"pb":2.79,"eps":32.95,"bv":246.1,"roe":null,"divYield":75.0,"w52h":1120.0,"w52l":522.0,"ma50":725.18,"ma200":820.34,"beta":-0.35,"opm":14.55,"npm":9.92},"DRREDDY":{"sym":"DRREDDY","name":"Dr. Reddy's Laboratories Limited","sector":"Healthcare","ltp":1262.4,"change":9.1,"changePct":0.726,"open":1267.2,"high":1279.8,"low":1250.3,"prev":1253.3,"vol":1411766,"avgVol":1595502,"mktCap":1051063025664,"pe":18.58,"fwdPe":22.98,"pb":2.82,"eps":67.93,"bv":447.25,"roe":16.1,"divYield":64.0,"w52h":1379.7,"w52l":1020.0,"ma50":1257.16,"ma200":1261.18,"beta":0.31,"opm":16.42,"npm":16.36},"ENGINERSIN":{"sym":"ENGINERSIN","name":"Engineers India Limited","sector":"Industrials","ltp":185.52,"change":4.23,"changePct":2.333,"open":188.0,"high":188.0,"low":183.1,"prev":181.29,"vol":1054689,"avgVol":9509793,"mktCap":104353005568,"pe":13.43,"fwdPe":15.77,"pb":3.84,"eps":13.81,"bv":48.28,"roe":null,"divYield":165.0,"w52h":255.45,"w52l":148.81,"ma50":192.76,"ma200":203.69,"beta":0.7,"opm":28.26,"npm":19.34},"FINCABLES":{"sym":"FINCABLES","name":"Finolex Cables Limited","sector":"Industrials","ltp":820.1,"change":11.5,"changePct":1.422,"open":834.0,"high":834.8,"low":811.7,"prev":808.6,"vol":250504,"avgVol":453284,"mktCap":125425549312,"pe":18.41,"fwdPe":15.08,"pb":2.2,"eps":44.55,"bv":372.71,"roe":null,"divYield":99.0,"w52h":1028.0,"w52l":700.8,"ma50":812.8,"ma200":826.24,"beta":0.16,"opm":8.92,"npm":11.42},"GRSE":{"sym":"GRSE","name":"Garden Reach Shipbuilders & Engineers Limited","sector":"Industrials","ltp":2140.9,"change":4.7,"changePct":0.22,"open":2200.0,"high":2249.0,"low":2120.5,"prev":2136.2,"vol":519617,"avgVol":1198215,"mktCap":245422014464,"pe":35.56,"fwdPe":26.93,"pb":10.68,"eps":60.24,"bv":200.49,"roe":null,"divYield":125.0,"w52h":3538.4,"w52l":1405.0,"ma50":2428.47,"ma200":2578.43,"beta":0.25,"opm":8.42,"npm":10.56},"GESHIP":{"sym":"GESHIP","name":"The Great Eastern Shipping Company Limited","sector":"Industrials","ltp":1390.0,"change":30.0,"changePct":2.206,"open":1405.0,"high":1418.1,"low":1373.0,"prev":1360.0,"vol":180728,"avgVol":530934,"mktCap":198446366720,"pe":8.8,"fwdPe":8.61,"pb":1.3,"eps":158.03,"bv":1066.28,"roe":null,"divYield":212.0,"w52h":1509.0,"w52l":802.25,"ma50":1280.41,"ma200":1093.6,"beta":0.7,"opm":38.18,"npm":44.16},"HDFCBANK":{"sym":"HDFCBANK","name":"HDFC Bank Limited","sector":"Financial Services","ltp":756.95,"change":12.8,"changePct":1.72,"open":755.0,"high":759.7,"low":747.7,"prev":744.15,"vol":22925790,"avgVol":34341753,"mktCap":11650908291072,"pe":16.9,"fwdPe":13.26,"pb":2.06,"eps":44.8,"bv":367.24,"roe":14.02,"divYield":148.0,"w52h":1020.5,"w52l":747.7,"ma50":900.26,"ma200":964.53,"beta":0.36,"opm":34.79,"npm":26.19},"HDFCLIFE":{"sym":"HDFCLIFE","name":"HDFC Life Insurance Company Limited","sector":"Financial Services","ltp":594.7,"change":2.6,"changePct":0.439,"open":597.0,"high":600.5,"low":590.05,"prev":592.1,"vol":1043405,"avgVol":3016741,"mktCap":1282934308864,"pe":67.89,"fwdPe":53.37,"pb":7.28,"eps":8.76,"bv":81.65,"roe":11.32,"divYield":35.0,"w52h":820.75,"w52l":590.05,"ma50":702.84,"ma200":749.39,"beta":0.48,"opm":1.51,"npm":1.81},"HAL":{"sym":"HAL","name":"Hindustan Aeronautics Limited","sector":"Industrials","ltp":3648.1,"change":13.5,"changePct":0.371,"open":3700.0,"high":3723.3,"low":3620.7,"prev":3634.6,"vol":528952,"avgVol":1565018,"mktCap":2439757955072,"pe":27.42,"fwdPe":24.47,"pb":6.57,"eps":133.03,"bv":555.02,"roe":null,"divYield":138.0,"w52h":5165.0,"w52l":3620.7,"ma50":4167.67,"ma200":4520.79,"beta":0.3,"opm":15.11,"npm":27.08},"HINDCOPPER":{"sym":"HINDCOPPER","name":"Hindustan Copper Limited","sector":"Basic Materials","ltp":454.1,"change":4.95,"changePct":1.102,"open":463.6,"high":467.0,"low":447.0,"prev":449.15,"vol":5066385,"avgVol":37036976,"mktCap":439295082496,"pe":66.49,"fwdPe":23.17,"pb":14.81,"eps":6.83,"bv":30.66,"roe":null,"divYield":55.0,"w52h":760.05,"w52l":183.82,"ma50":567.0,"ma200":380.96,"beta":1.59,"opm":28.6,"npm":24.93},"HINDZINC":{"sym":"HINDZINC","name":"Hindustan Zinc Limited","sector":"Basic Materials","ltp":490.5,"change":2.85,"changePct":0.584,"open":499.0,"high":499.0,"low":484.75,"prev":487.65,"vol":3278672,"avgVol":14301888,"mktCap":2072518983680,"pe":17.56,"fwdPe":12.57,"pb":15.13,"eps":27.94,"bv":32.42,"roe":null,"divYield":563.0,"w52h":733.0,"w52l":388.55,"ma50":614.18,"ma200":514.11,"beta":0.49,"opm":48.06,"npm":33.23},"ICICIBANK":{"sym":"ICICIBANK","name":"ICICI Bank Limited","sector":"Financial Services","ltp":1229.7,"change":7.0,"changePct":0.573,"open":1237.1,"high":1246.0,"low":1226.0,"prev":1222.7,"vol":4810815,"avgVol":14581032,"mktCap":8802959097856,"pe":16.79,"fwdPe":15.47,"pb":2.52,"eps":73.24,"bv":487.64,"roe":16.8,"divYield":90.0,"w52h":1500.0,"w52l":1226.0,"ma50":1362.95,"ma200":1390.71,"beta":0.18,"opm":33.97,"npm":27.51},"IDEAFORGE":{"sym":"IDEAFORGE","name":"ideaForge Technology Limited","sector":"Technology","ltp":402.9,"change":5.3,"changePct":1.333,"open":410.0,"high":411.0,"low":396.0,"prev":397.6,"vol":152816,"avgVol":922221,"mktCap":17435871232,"pe":null,"fwdPe":28.37,"pb":3.1,"eps":-23.7,"bv":130.17,"roe":null,"divYield":null,"w52h":659.85,"w52l":304.2,"ma50":428.07,"ma200":476.81,"beta":1.31,"opm":-118.85,"npm":-97.47},"IDFCFIRSTB":{"sym":"IDFCFIRSTB","name":"IDFC First Bank Limited","sector":"Financial Services","ltp":61.46,"change":1.22,"changePct":2.025,"open":61.63,"high":61.99,"low":60.95,"prev":60.24,"vol":10599605,"avgVol":46820788,"mktCap":528630284288,"pe":32.35,"fwdPe":12.56,"pb":1.16,"eps":1.9,"bv":53.12,"roe":3.71,"divYield":42.0,"w52h":87.0,"w52l":52.46,"ma50":77.11,"ma200":76.03,"beta":0.33,"opm":9.83,"npm":6.96},"INDUSTOWER":{"sym":"INDUSTOWER","name":"Indus Towers Limited","sector":"Communication Services","ltp":423.8,"change":10.2,"changePct":2.466,"open":422.0,"high":425.2,"low":415.45,"prev":413.6,"vol":2500611,"avgVol":6685645,"mktCap":1117625516032,"pe":15.67,"fwdPe":14.34,"pb":2.95,"eps":27.05,"bv":143.57,"roe":20.31,"divYield":null,"w52h":481.5,"w52l":312.55,"ma50":444.22,"ma200":397.66,"beta":-0.03,"opm":33.27,"npm":22.2},"INOXINDIA":{"sym":"INOXINDIA","name":"INOX India Limited","sector":"Industrials","ltp":1190.5,"change":27.6,"changePct":2.373,"open":1192.0,"high":1198.0,"low":1160.0,"prev":1162.9,"vol":38139,"avgVol":63242,"mktCap":108053954560,"pe":43.75,"fwdPe":34.08,"pb":11.03,"eps":27.21,"bv":107.95,"roe":null,"divYield":17.0,"w52h":1288.0,"w52l":892.25,"ma50":1140.13,"ma200":1167.22,"beta":0.6,"opm":19.64,"npm":16.59},"INTERARCH":{"sym":"INTERARCH","name":"Interarch Building Solutions Limited","sector":"Industrials","ltp":1715.6,"change":42.0,"changePct":2.51,"open":1730.1,"high":1740.0,"low":1696.0,"prev":1673.6,"vol":23756,"avgVol":99700,"mktCap":28773789696,"pe":21.09,"fwdPe":15.61,"pb":3.59,"eps":81.34,"bv":477.32,"roe":null,"divYield":75.0,"w52h":2762.6,"w52l":1264.0,"ma50":1933.12,"ma200":2134.69,"beta":null,"opm":8.89,"npm":7.34},"ITC":{"sym":"ITC","name":"ITC Limited","sector":"Consumer Defensive","ltp":290.7,"change":0.25,"changePct":0.086,"open":295.95,"high":296.0,"low":288.75,"prev":290.45,"vol":18130760,"avgVol":29356913,"mktCap":3642316554240,"pe":17.87,"fwdPe":17.3,"pb":5.13,"eps":16.27,"bv":56.71,"roe":null,"divYield":494.0,"w52h":444.2,"w52l":288.75,"ma50":317.82,"ma200":383.8,"beta":-0.24,"opm":32.18,"npm":43.89},"INDIANB":{"sym":"INDIANB","name":"Indian Bank","sector":"Financial Services","ltp":865.55,"change":27.35,"changePct":3.263,"open":850.0,"high":871.9,"low":850.0,"prev":838.2,"vol":688190,"avgVol":2047673,"mktCap":1166282457088,"pe":10.12,"fwdPe":8.78,"pb":1.46,"eps":85.5,"bv":593.25,"roe":15.75,"divYield":194.0,"w52h":1000.0,"w52l":517.85,"ma50":900.92,"ma200":779.23,"beta":0.28,"opm":47.53,"npm":33.73},"IOC":{"sym":"IOC","name":"Indian Oil Corporation Limited","sector":"Energy","ltp":138.56,"change":0.45,"changePct":0.326,"open":141.58,"high":142.5,"low":137.02,"prev":138.11,"vol":11479223,"avgVol":16832112,"mktCap":1956638752768,"pe":5.34,"fwdPe":7.38,"pb":0.97,"eps":25.96,"bv":143.2,"roe":null,"divYield":724.0,"w52h":188.96,"w52l":122.35,"ma50":166.61,"ma200":156.59,"beta":0.76,"opm":8.91,"npm":4.64},"JYOTHYLAB":{"sym":"JYOTHYLAB","name":"Jyothy Labs Limited","sector":"Consumer Defensive","ltp":205.05,"change":5.45,"changePct":2.73,"open":205.0,"high":205.45,"low":200.3,"prev":199.6,"vol":478687,"avgVol":539156,"mktCap":75297333248,"pe":22.05,"fwdPe":19.47,"pb":5.24,"eps":9.3,"bv":39.16,"roe":null,"divYield":175.0,"w52h":399.9,"w52l":200.3,"ma50":243.25,"ma200":298.98,"beta":0.1,"opm":12.87,"npm":11.72},"KAYNES":{"sym":"KAYNES","name":"Kaynes Technology India Limited","sector":"Technology","ltp":3488.0,"change":78.3,"changePct":2.296,"open":3515.0,"high":3526.6,"low":3411.2,"prev":3409.7,"vol":663083,"avgVol":1616769,"mktCap":233994584064,"pe":58.79,"fwdPe":39.62,"pb":4.87,"eps":59.33,"bv":715.5,"roe":null,"divYield":null,"w52h":7705.0,"w52l":3294.9,"ma50":3706.18,"ma200":5390.33,"beta":-0.46,"opm":12.3,"npm":11.54},"KEI":{"sym":"KEI","name":"KEI Industries Limited","sector":"Industrials","ltp":4036.0,"change":45.5,"changePct":1.14,"open":4123.5,"high":4123.5,"low":4000.0,"prev":3990.5,"vol":165912,"avgVol":354063,"mktCap":385843986432,"pe":44.75,"fwdPe":35.1,"pb":6.23,"eps":90.19,"bv":647.65,"roe":null,"divYield":11.0,"w52h":5303.0,"w52l":2424.0,"ma50":4418.59,"ma200":4134.07,"beta":0.2,"opm":10.07,"npm":7.69},"MAITHANALL":{"sym":"MAITHANALL","name":"Maithan Alloys Limited","sector":"Basic Materials","ltp":872.1,"change":7.5,"changePct":0.867,"open":895.0,"high":895.0,"low":866.8,"prev":864.6,"vol":21099,"avgVol":194880,"mktCap":25388181504,"pe":5.73,"fwdPe":null,"pb":0.62,"eps":152.17,"bv":1416.4,"roe":null,"divYield":254.0,"w52h":1264.0,"w52l":835.25,"ma50":1008.19,"ma200":1063.49,"beta":0.38,"opm":10.13,"npm":21.63},"MARKSANS":{"sym":"MARKSANS","name":"Marksans Pharma Limited","sector":"Healthcare","ltp":161.95,"change":1.75,"changePct":1.092,"open":163.0,"high":165.33,"low":159.7,"prev":160.2,"vol":519637,"avgVol":691714,"mktCap":73389867008,"pe":20.37,"fwdPe":14.72,"pb":2.73,"eps":7.95,"bv":59.37,"roe":null,"divYield":50.0,"w52h":270.7,"w52l":156.0,"ma50":172.87,"ma200":191.42,"beta":1.04,"opm":18.08,"npm":12.85},"NCC":{"sym":"NCC","name":"NCC Limited","sector":"Industrials","ltp":134.19,"change":1.9,"changePct":1.436,"open":137.0,"high":137.5,"low":132.44,"prev":132.29,"vol":1188589,"avgVol":3784560,"mktCap":84250738688,"pe":11.66,"fwdPe":9.9,"pb":1.12,"eps":11.51,"bv":119.81,"roe":null,"divYield":166.0,"w52h":242.15,"w52l":132.44,"ma50":148.18,"ma200":187.59,"beta":0.32,"opm":7.76,"npm":3.49},"NETWEB":{"sym":"NETWEB","name":"Netweb Technologies India Limited","sector":"Technology","ltp":3128.7,"change":41.1,"changePct":1.331,"open":3193.9,"high":3232.3,"low":3117.3,"prev":3087.6,"vol":601525,"avgVol":2115510,"mktCap":178308890624,"pe":99.36,"fwdPe":47.29,"pb":30.62,"eps":31.49,"bv":102.17,"roe":null,"divYield":8.0,"w52h":4479.0,"w52l":1251.55,"ma50":3287.06,"ma200":2995.83,"beta":1.73,"opm":11.72,"npm":9.79},"OIL":{"sym":"OIL","name":"Oil India Limited","sector":"Energy","ltp":474.2,"change":9.55,"changePct":2.055,"open":461.85,"high":475.15,"low":461.15,"prev":464.65,"vol":1236749,"avgVol":6009176,"mktCap":771610050560,"pe":13.24,"fwdPe":9.99,"pb":1.37,"eps":35.82,"bv":345.7,"roe":null,"divYield":409.0,"w52h":524.0,"w52l":325.0,"ma50":472.43,"ma200":434.11,"beta":0.31,"opm":21.56,"npm":17.41},"PVRINOX":{"sym":"PVRINOX","name":"PVR INOX Limited","sector":"Communication Services","ltp":945.0,"change":3.1,"changePct":0.329,"open":954.9,"high":963.9,"low":936.7,"prev":941.9,"vol":174314,"avgVol":391055,"mktCap":92798959616,"pe":435.48,"fwdPe":23.05,"pb":1.3,"eps":2.17,"bv":724.6,"roe":null,"divYield":null,"w52h":1249.7,"w52l":830.0,"ma50":1008.93,"ma200":1052.36,"beta":0.22,"opm":16.23,"npm":0.35},"PFC":{"sym":"PFC","name":"Power Finance Corporation Limited","sector":"Financial Services","ltp":399.0,"change":1.0,"changePct":0.251,"open":408.45,"high":409.65,"low":396.5,"prev":398.0,"vol":5167551,"avgVol":8674175,"mktCap":1316740530176,"pe":5.22,"fwdPe":6.75,"pb":1.04,"eps":76.42,"bv":384.79,"roe":null,"divYield":367.0,"w52h":444.1,"w52l":329.9,"ma50":398.78,"ma200":393.64,"beta":0.6,"opm":93.41,"npm":50.51},"POWERGRID":{"sym":"POWERGRID","name":"Power Grid Corporation of India Limited","sector":"Utilities","ltp":297.7,"change":-4.4,"changePct":-1.456,"open":309.0,"high":309.0,"low":292.4,"prev":302.1,"vol":11615858,"avgVol":15509801,"mktCap":2768789831680,"pe":19.1,"fwdPe":16.08,"pb":2.79,"eps":15.59,"bv":106.53,"roe":null,"divYield":405.0,"w52h":322.0,"w52l":250.0,"ma50":284.38,"ma200":282.6,"beta":0.22,"opm":58.66,"npm":32.79},"RECLTD":{"sym":"RECLTD","name":"REC Limited","sector":"Financial Services","ltp":318.45,"change":2.0,"changePct":0.632,"open":322.5,"high":325.8,"low":312.05,"prev":316.45,"vol":4001416,"avgVol":9228175,"mktCap":838667730944,"pe":4.87,"fwdPe":4.71,"pb":1.0,"eps":65.38,"bv":317.1,"roe":21.47,"divYield":733.0,"w52h":450.0,"w52l":312.05,"ma50":354.32,"ma200":369.56,"beta":0.21,"opm":95.83,"npm":72.19},"REDTAPE":{"sym":"REDTAPE","name":"REDTAPE Limited","sector":"Consumer Cyclical","ltp":115.14,"change":2.52,"changePct":2.238,"open":114.31,"high":119.9,"low":112.2,"prev":112.62,"vol":309960,"avgVol":661282,"mktCap":63650267136,"pe":29.98,"fwdPe":null,"pb":7.4,"eps":3.84,"bv":15.56,"roe":null,"divYield":44.0,"w52h":167.97,"w52l":107.53,"ma50":121.62,"ma200":129.54,"beta":-0.72,"opm":18.81,"npm":9.42},"RAIN":{"sym":"RAIN","name":"Rain Industries Limited","sector":"Basic Materials","ltp":103.57,"change":0.71,"changePct":0.69,"open":106.78,"high":106.78,"low":102.75,"prev":102.86,"vol":1130053,"avgVol":4524493,"mktCap":34835320832,"pe":82.86,"fwdPe":-68.14,"pb":0.47,"eps":1.25,"bv":220.57,"roe":1.87,"divYield":97.0,"w52h":176.0,"w52l":99.9,"ma50":141.89,"ma200":137.46,"beta":0.51,"opm":5.81,"npm":0.25},"RATEGAIN":{"sym":"RATEGAIN","name":"RateGain Travel Technologies Limited","sector":"Technology","ltp":471.05,"change":4.3,"changePct":0.921,"open":482.0,"high":482.0,"low":460.0,"prev":466.75,"vol":147231,"avgVol":414499,"mktCap":55610507264,"pe":31.05,"fwdPe":21.32,"pb":3.06,"eps":15.17,"bv":153.85,"roe":null,"divYield":null,"w52h":741.6,"w52l":412.85,"ma50":564.17,"ma200":581.93,"beta":0.36,"opm":11.01,"npm":13.09},"REPCOHOME":{"sym":"REPCOHOME","name":"Repco Home Finance Limited","sector":"Financial Services","ltp":340.5,"change":3.9,"changePct":1.159,"open":347.65,"high":347.65,"low":339.05,"prev":336.6,"vol":42076,"avgVol":99740,"mktCap":21302142976,"pe":4.62,"fwdPe":4.63,"pb":0.59,"eps":73.65,"bv":577.19,"roe":null,"divYield":253.0,"w52h":464.45,"w52l":315.2,"ma50":389.06,"ma200":398.86,"beta":0.41,"opm":66.57,"npm":55.46},"SAGILITY":{"sym":"SAGILITY","name":"Sagility Limited","sector":"Healthcare","ltp":36.65,"change":0.3,"changePct":0.825,"open":37.08,"high":37.34,"low":36.25,"prev":36.35,"vol":9695114,"avgVol":30873861,"mktCap":171570708480,"pe":20.25,"fwdPe":15.47,"pb":1.95,"eps":1.81,"bv":18.79,"roe":null,"divYield":28.0,"w52h":57.89,"w52l":36.25,"ma50":45.56,"ma200":46.4,"beta":null,"opm":19.66,"npm":12.61},"SUZLON":{"sym":"SUZLON","name":"Suzlon Energy Limited","sector":"Industrials","ltp":40.55,"change":0.61,"changePct":1.527,"open":41.3,"high":41.3,"low":39.95,"prev":39.94,"vol":32154087,"avgVol":61885656,"mktCap":556136267776,"pe":17.18,"fwdPe":20.47,"pb":7.1,"eps":2.36,"bv":5.71,"roe":null,"divYield":null,"w52h":74.3,"w52l":38.19,"ma50":44.95,"ma200":54.79,"beta":0.42,"opm":15.64,"npm":21.56},"SANDUMA":{"sym":"SANDUMA","name":"The Sandur Manganese & Iron Ores Limited","sector":"Basic Materials","ltp":173.82,"change":2.23,"changePct":1.3,"open":175.0,"high":177.36,"low":172.1,"prev":171.59,"vol":392200,"avgVol":3829581,"mktCap":84515627008,"pe":14.64,"fwdPe":null,"pb":2.91,"eps":11.87,"bv":59.7,"roe":null,"divYield":24.0,"w52h":273.0,"w52l":125.77,"ma50":208.74,"ma200":191.36,"beta":0.57,"opm":16.3,"npm":11.79},"SBIN":{"sym":"SBIN","name":"State Bank of India","sector":"Financial Services","ltp":1030.0,"change":-1.9,"changePct":-0.184,"open":1055.2,"high":1059.0,"low":1028.2,"prev":1031.9,"vol":8445964,"avgVol":13185188,"mktCap":9507536109568,"pe":11.22,"fwdPe":11.1,"pb":1.61,"eps":91.84,"bv":641.36,"roe":null,"divYield":154.0,"w52h":1234.7,"w52l":730.0,"ma50":1110.3,"ma200":939.21,"beta":0.3,"opm":29.68,"npm":22.5},"SUNFLAG":{"sym":"SUNFLAG","name":"Sunflag Iron and Steel Company Limited","sector":"Basic Materials","ltp":208.79,"change":1.59,"changePct":0.767,"open":209.5,"high":212.1,"low":207.46,"prev":207.2,"vol":54990,"avgVol":138220,"mktCap":37628018688,"pe":17.8,"fwdPe":null,"pb":0.44,"eps":11.73,"bv":474.63,"roe":null,"divYield":36.0,"w52h":322.0,"w52l":196.37,"ma50":241.24,"ma200":265.62,"beta":0.47,"opm":10.74,"npm":5.53},"SUPRIYA":{"sym":"SUPRIYA","name":"Supriya Lifescience Limited","sector":"Healthcare","ltp":559.95,"change":6.6,"changePct":1.193,"open":562.3,"high":579.0,"low":545.5,"prev":553.35,"vol":160352,"avgVol":147593,"mktCap":45066346496,"pe":24.32,"fwdPe":18.27,"pb":4.16,"eps":23.02,"bv":134.51,"roe":null,"divYield":18.0,"w52h":842.0,"w52l":545.5,"ma50":666.76,"ma200":702.43,"beta":0.14,"opm":31.61,"npm":25.19},"TDPOWERSYS":{"sym":"TDPOWERSYS","name":"TD Power Systems Limited","sector":"Industrials","ltp":855.95,"change":36.25,"changePct":4.422,"open":839.0,"high":857.5,"low":834.4,"prev":819.7,"vol":300362,"avgVol":954962,"mktCap":133712084992,"pe":61.05,"fwdPe":46.77,"pb":13.92,"eps":14.02,"bv":61.49,"roe":null,"divYield":24.0,"w52h":933.0,"w52l":318.7,"ma50":791.61,"ma200":655.63,"beta":0.2,"opm":16.84,"npm":13.6},"TRUALT":{"sym":"TRUALT","name":"TRUALT BIOENERGY LIMITED","sector":"Energy","ltp":389.0,"change":4.2,"changePct":1.091,"open":395.5,"high":395.5,"low":382.05,"prev":384.8,"vol":45104,"avgVol":196092,"mktCap":33390798848,"pe":22.56,"fwdPe":null,"pb":1.96,"eps":17.24,"bv":198.37,"roe":null,"divYield":null,"w52h":549.0,"w52l":310.2,"ma50":388.97,"ma200":418.83,"beta":null,"opm":15.73,"npm":8.82},"TATAPOWER":{"sym":"TATAPOWER","name":"Tata Power Company Limited","sector":"Utilities","ltp":386.6,"change":-0.35,"changePct":-0.09,"open":395.0,"high":395.0,"low":384.65,"prev":386.95,"vol":4094877,"avgVol":5238805,"mktCap":1235318341632,"pe":32.65,"fwdPe":22.87,"pb":3.26,"eps":11.84,"bv":118.48,"roe":null,"divYield":58.0,"w52h":418.45,"w52l":335.0,"ma50":372.67,"ma200":386.11,"beta":0.28,"opm":13.24,"npm":5.87},"VENTIVE":{"sym":"VENTIVE","name":"VENTIVE HOSPITALITY LTD","sector":"Consumer Cyclical","ltp":617.8,"change":-5.15,"changePct":-0.827,"open":627.85,"high":627.85,"low":613.65,"prev":622.95,"vol":51009,"avgVol":100353,"mktCap":144282009600,"pe":39.35,"fwdPe":32.42,"pb":2.9,"eps":15.7,"bv":213.09,"roe":null,"divYield":null,"w52h":840.0,"w52l":613.65,"ma50":723.61,"ma200":733.1,"beta":null,"opm":33.07,"npm":15.43},"VEDL":{"sym":"VEDL","name":"Vedanta Limited","sector":"Basic Materials","ltp":646.8,"change":1.05,"changePct":0.163,"open":664.0,"high":664.0,"low":643.55,"prev":645.75,"vol":5794621,"avgVol":16631231,"mktCap":2527804784640,"pe":17.95,"fwdPe":8.62,"pb":6.28,"eps":36.03,"bv":102.93,"roe":null,"divYield":766.0,"w52h":769.8,"w52l":363.0,"ma50":691.46,"ma200":538.04,"beta":0.73,"opm":23.68,"npm":8.83},"VOLTAMP":{"sym":"VOLTAMP","name":"Voltamp Transformers Limited","sector":"Industrials","ltp":8420.0,"change":119.0,"changePct":1.434,"open":8520.0,"high":8520.0,"low":8357.0,"prev":8301.0,"vol":7083,"avgVol":35958,"mktCap":85186150400,"pe":24.04,"fwdPe":22.77,"pb":5.18,"eps":350.3,"bv":1625.69,"roe":null,"divYield":120.0,"w52h":10088.0,"w52l":6099.95,"ma50":7991.73,"ma200":8041.76,"beta":-0.37,"opm":16.49,"npm":16.37},"ZENTEC":{"sym":"ZENTEC","name":"Zen Technologies Limited","sector":"Industrials","ltp":1365.9,"change":8.1,"changePct":0.597,"open":1370.0,"high":1398.0,"low":1356.1,"prev":1357.8,"vol":124300,"avgVol":533303,"mktCap":122914660352,"pe":46.59,"fwdPe":33.46,"pb":6.84,"eps":29.33,"bv":199.84,"roe":null,"divYield":15.0,"w52h":2268.0,"w52l":1223.0,"ma50":1349.39,"ma200":1475.64,"beta":-0.34,"opm":33.91,"npm":31.51},"BLACKBUCK":{"sym":"BLACKBUCK","name":"BlackBuck Limited","sector":"Technology","ltp":577.2,"change":-9.8,"changePct":-1.67,"open":594.0,"high":595.4,"low":571.35,"prev":587.0,"vol":187651,"avgVol":758933,"mktCap":104861286400,"pe":27.54,"fwdPe":44.48,"pb":8.02,"eps":20.96,"bv":72.0,"roe":null,"divYield":null,"w52h":748.0,"w52l":373.2,"ma50":596.49,"ma200":584.14,"beta":null,"opm":18.17,"npm":63.72},"AMARAJAB":{"sym":"AMARAJAB","name":"Amara Raja Energy & Mobility Limited","sector":"Industrials","ltp":726.35,"change":-0.65,"changePct":-0.089,"open":748.0,"high":748.0,"low":722.4,"prev":727.0,"vol":179281,"avgVol":314061,"mktCap":132955086848,"pe":17.9,"fwdPe":13.69,"pb":1.72,"eps":40.57,"bv":422.83,"roe":null,"divYield":149.0,"w52h":1109.0,"w52l":722.4,"ma50":839.75,"ma200":942.3,"beta":0.54,"opm":6.36,"npm":5.57},"CAPITALNUMB":{"sym":"CAPITALNUMB","name":"CapitalNumbers Infotech Limited","sector":"Technology","ltp":81.0,"change":-3.93,"changePct":-4.627,"open":82.6,"high":83.5,"low":80.02,"prev":84.93,"vol":16400,"avgVol":28233,"mktCap":1978586368,"pe":7.35,"fwdPe":null,"pb":1.15,"eps":11.02,"bv":70.36,"roe":null,"divYield":235.0,"w52h":189.9,"w52l":79.22,"ma50":93.74,"ma200":114.11,"beta":null,"opm":25.16,"npm":26.32},"CELLOWORLD":{"sym":"CELLOWORLD","name":"Cello World Limited","sector":"Consumer Cyclical","ltp":419.8,"change":22.2,"changePct":5.584,"open":411.3,"high":427.5,"low":394.35,"prev":397.6,"vol":744419,"avgVol":162195,"mktCap":92753190912,"pe":29.99,"fwdPe":24.23,"pb":4.05,"eps":14.0,"bv":103.61,"roe":null,"divYield":38.0,"w52h":673.8,"w52l":384.3,"ma50":462.59,"ma200":558.11,"beta":0.2,"opm":17.95,"npm":13.39},"CIGNITI":{"sym":"CIGNITI","name":"Cigniti Technologies Limited","sector":"Technology","ltp":1083.8,"change":10.4,"changePct":0.969,"open":1086.2,"high":1090.5,"low":1058.4,"prev":1073.4,"vol":25881,"avgVol":80074,"mktCap":29855395840,"pe":9.92,"fwdPe":null,"pb":2.65,"eps":109.27,"bv":409.66,"roe":null,"divYield":null,"w52h":1929.5,"w52l":996.5,"ma50":1387.06,"ma200":1613.72,"beta":-0.29,"opm":17.09,"npm":13.66},"HBLPOWER":{"sym":"HBLPOWER","name":"HBL ENGINEERING LTD","sector":"Industrials","ltp":648.7,"change":23.1,"changePct":3.692,"open":640.0,"high":666.45,"low":639.0,"prev":625.6,"vol":1488438,"avgVol":1884211,"mktCap":179816366080,"pe":22.59,"fwdPe":null,"pb":9.07,"eps":28.72,"bv":71.56,"roe":null,"divYield":32.0,"w52h":1122.0,"w52l":440.1,"ma50":736.1,"ma200":775.85,"beta":-0.35,"opm":33.19,"npm":25.08},"HIGHENERGYB":{"sym":"HIGHENERGYB","name":"High Energy Batteries (India) Limited","sector":"Industrials","ltp":516.0,"change":18.0,"changePct":3.614,"open":515.95,"high":517.75,"low":501.2,"prev":498.0,"vol":2241,"avgVol":7438,"mktCap":4625341440,"pe":26.03,"fwdPe":null,"pb":4.65,"eps":19.82,"bv":111.04,"roe":null,"divYield":60.0,"w52h":830.35,"w52l":432.0,"ma50":552.56,"ma200":615.61,"beta":-0.17,"opm":31.49,"npm":19.79},"HINDRECTIF":{"sym":"HINDRECTIF","name":"Hind Rectifiers Limited","sector":"Industrials","ltp":1497.0,"change":61.7,"changePct":4.299,"open":1479.0,"high":1499.0,"low":1464.1,"prev":1435.3,"vol":12737,"avgVol":47552,"mktCap":25724160000,"pe":51.13,"fwdPe":null,"pb":13.51,"eps":29.28,"bv":110.83,"roe":null,"divYield":14.0,"w52h":2108.5,"w52l":799.0,"ma50":1357.53,"ma200":1512.14,"beta":-0.15,"opm":7.6,"npm":5.58},"IGI":{"sym":"IGI","name":"International Gemmological Institute (India) Limited","sector":"Basic Materials","ltp":326.15,"change":7.35,"changePct":2.306,"open":325.8,"high":327.8,"low":320.0,"prev":318.8,"vol":285084,"avgVol":861642,"mktCap":140948881408,"pe":27.5,"fwdPe":0.23,"pb":10.01,"eps":11.86,"bv":32.58,"roe":43.0,"divYield":157.0,"w52h":442.0,"w52l":287.0,"ma50":321.51,"ma200":346.31,"beta":null,"opm":56.1,"npm":43.25},"AZADINDIA":{"sym":"AZADINDIA","name":"Azad India Mobility Ltd","sector":"Basic Materials","ltp":83.0,"change":-2.83,"changePct":-3.297,"open":89.59,"high":89.59,"low":83.0,"prev":85.83,"vol":2205,"avgVol":9155,"mktCap":4518781440,"pe":296.43,"fwdPe":null,"pb":3.73,"eps":0.28,"bv":22.27,"roe":null,"divYield":null,"w52h":176.8,"w52l":75.15,"ma50":100.81,"ma200":132.78,"beta":-0.9,"opm":0.68,"npm":1.95},"INDOTECHTR":{"sym":"INDOTECHTR","name":"Indo Tech Transformers Limited","sector":"Industrials","ltp":1228.0,"change":-5.5,"changePct":-0.446,"open":1285.0,"high":1285.0,"low":1217.2,"prev":1233.5,"vol":12198,"avgVol":34415,"mktCap":13048884224,"pe":14.51,"fwdPe":null,"pb":4.02,"eps":84.62,"bv":305.62,"roe":null,"divYield":null,"w52h":2787.4,"w52l":1148.0,"ma50":1375.54,"ma200":1662.01,"beta":-0.67,"opm":16.19,"npm":11.99},"KPENERGI":{"sym":"KPENERGI","name":"K.P. Energy Limited","sector":"Industrials","ltp":265.15,"change":0.65,"changePct":0.246,"open":274.0,"high":274.0,"low":260.4,"prev":264.5,"vol":137054,"avgVol":324635,"mktCap":17958459392,"pe":12.02,"fwdPe":null,"pb":4.71,"eps":22.06,"bv":56.27,"roe":null,"divYield":28.0,"w52h":583.7,"w52l":237.9,"ma50":294.85,"ma200":399.71,"beta":-0.21,"opm":19.12,"npm":11.73},"KWALITYPHARM":{"sym":"KWALITYPHARM","name":"Kwality Pharmaceuticals Limited","sector":"Healthcare","ltp":1483.95,"change":27.8,"changePct":1.909,"open":1471.5,"high":1526.9,"low":1470.0,"prev":1456.15,"vol":8068,"avgVol":33162,"mktCap":15397758976,"pe":27.25,"fwdPe":null,"pb":5.31,"eps":54.46,"bv":279.5,"roe":null,"divYield":null,"w52h":1740.0,"w52l":666.0,"ma50":1308.23,"ma200":1079.75,"beta":-0.12,"opm":20.79,"npm":12.25},"MBENGINEERING":{"sym":"MBENGINEERING","name":"M AND B ENGINEERING LTD","sector":"Industrials","ltp":247.3,"change":-0.7,"changePct":-0.282,"open":252.0,"high":253.5,"low":243.1,"prev":248.0,"vol":79884,"avgVol":189915,"mktCap":14132754432,"pe":15.02,"fwdPe":10.66,"pb":2.27,"eps":16.47,"bv":109.07,"roe":null,"divYield":null,"w52h":535.9,"w52l":243.1,"ma50":316.6,"ma200":383.04,"beta":null,"opm":10.47,"npm":7.78},"QUALPOWER":{"sym":"QUALPOWER","name":"QUALITY POWER ELEC EQUP L","sector":"Industrials","ltp":829.5,"change":32.75,"changePct":4.11,"open":817.0,"high":854.7,"low":812.1,"prev":796.75,"vol":991788,"avgVol":1223193,"mktCap":64239878144,"pe":60.2,"fwdPe":22.66,"pb":13.67,"eps":13.78,"bv":60.66,"roe":null,"divYield":13.0,"w52h":1082.0,"w52l":267.8,"ma50":770.17,"ma200":810.03,"beta":null,"opm":26.58,"npm":13.79},"REVATHI":{"sym":"REVATHI","name":"Revathi Equipment India Limited","sector":"Industrials","ltp":525.0,"change":-16.7,"changePct":-3.083,"open":542.6,"high":542.6,"low":525.0,"prev":541.7,"vol":368,"avgVol":1810,"mktCap":1618007424,"pe":18.05,"fwdPe":null,"pb":1.28,"eps":29.09,"bv":411.56,"roe":null,"divYield":null,"w52h":1300.0,"w52l":491.1,"ma50":628.48,"ma200":841.54,"beta":null,"opm":-2.98,"npm":6.3},"ROSSELLTECH":{"sym":"ROSSELLTECH","name":"Rossell Techsys Limited","sector":"Industrials","ltp":693.95,"change":20.05,"changePct":2.975,"open":679.0,"high":703.7,"low":679.0,"prev":673.9,"vol":14889,"avgVol":184785,"mktCap":26259251200,"pe":124.14,"fwdPe":null,"pb":18.51,"eps":5.59,"bv":37.49,"roe":null,"divYield":3.0,"w52h":840.0,"w52l":277.05,"ma50":680.25,"ma200":630.9,"beta":null,"opm":10.53,"npm":4.91},"SSPOWERSWIT":{"sym":"SSPOWERSWIT","name":"S&S Power Switchgear Limited","sector":"Industrials","ltp":331.0,"change":6.0,"changePct":1.846,"open":331.45,"high":331.45,"low":331.0,"prev":325.0,"vol":408,"avgVol":3073,"mktCap":4085052928,"pe":50.69,"fwdPe":null,"pb":5.19,"eps":6.53,"bv":63.75,"roe":null,"divYield":null,"w52h":468.9,"w52l":193.5,"ma50":299.78,"ma200":339.0,"beta":0.44,"opm":5.16,"npm":3.16},"SHREEREFRI":{"sym":"SHREEREFRI","name":"SHREE REFRIGERATIONS LIMITED","sector":"Industrials","ltp":187.1,"change":8.2,"changePct":4.584,"open":185.0,"high":191.0,"low":184.9,"prev":178.9,"vol":57000,"avgVol":68658,"mktCap":6666449408,"pe":99.52,"fwdPe":null,"pb":2.93,"eps":1.88,"bv":63.75,"roe":null,"divYield":null,"w52h":311.5,"w52l":153.0,"ma50":179.61,"ma200":204.24,"beta":null,"opm":6.06,"npm":7.13},"SKMEPEX":{"sym":"SKMEPEX","name":"SKM Egg Products Export (India) Limited","sector":"Consumer Defensive","ltp":155.63,"change":4.13,"changePct":2.726,"open":155.99,"high":156.36,"low":152.17,"prev":151.5,"vol":31795,"avgVol":335540,"mktCap":8205657600,"pe":14.94,"fwdPe":null,"pb":2.42,"eps":10.42,"bv":64.34,"roe":null,"divYield":50.0,"w52h":232.5,"w52l":77.0,"ma50":174.16,"ma200":175.05,"beta":-0.48,"opm":19.09,"npm":11.08},"SHILCHAR":{"sym":"SHILCHAR","name":"Shilchar Technologies Limited","sector":"Industrials","ltp":3796.2,"change":23.4,"changePct":0.62,"open":3899.8,"high":3911.9,"low":3757.5,"prev":3772.8,"vol":13205,"avgVol":40435,"mktCap":43429285888,"pe":23.46,"fwdPe":null,"pb":10.34,"eps":161.85,"bv":367.01,"roe":null,"divYield":null,"w52h":4350.0,"w52l":2852.5,"ma50":3675.18,"ma200":3773.28,"beta":-0.83,"opm":30.23,"npm":25.12},"SIKAINTERP":{"sym":"SIKAINTERP","name":"Sika Interplant Systems Limited","sector":"Industrials","ltp":907.4,"change":1.85,"changePct":0.204,"open":915.05,"high":934.0,"low":904.0,"prev":905.55,"vol":6464,"avgVol":25625,"mktCap":19237675008,"pe":52.73,"fwdPe":null,"pb":13.04,"eps":17.21,"bv":69.61,"roe":27.67,"divYield":27.0,"w52h":1624.95,"w52l":511.0,"ma50":933.01,"ma200":1105.28,"beta":-0.13,"opm":22.53,"npm":16.9},"SUYOGTELE":{"sym":"SUYOGTELE","name":"Suyog Telematics Limited","sector":"Communication Services","ltp":602.25,"change":-9.25,"changePct":-1.513,"open":628.6,"high":629.45,"low":597.15,"prev":611.5,"vol":18414,"avgVol":34827,"mktCap":7056635392,"pe":26.98,"fwdPe":null,"pb":1.55,"eps":22.32,"bv":388.88,"roe":null,"divYield":29.0,"w52h":989.0,"w52l":526.5,"ma50":620.8,"ma200":737.33,"beta":0.08,"opm":42.85,"npm":16.12},"TITANBIOTE":{"sym":"TITANBIOTE","name":"Titan Biotech Limited","sector":"Healthcare","ltp":396.0,"change":8.6,"changePct":2.22,"open":405.0,"high":405.0,"low":392.05,"prev":387.4,"vol":26264,"avgVol":98739,"mktCap":16362126336,"pe":60.09,"fwdPe":null,"pb":9.83,"eps":6.59,"bv":40.29,"roe":null,"divYield":10.0,"w52h":408.9,"w52l":74.73,"ma50":252.38,"ma200":179.74,"beta":0.37,"opm":16.92,"npm":14.13},"MCDOWELL-N":{"sym":"MCDOWELL-N","name":"UNITED SPIRITS LIMITED","sector":"Consumer Defensive","ltp":1306.5,"change":31.3,"changePct":2.455,"open":1290.9,"high":1307.4,"low":1282.7,"prev":1275.2,"vol":354786,"avgVol":926301,"mktCap":950349660160,"pe":53.92,"fwdPe":46.14,"pb":11.04,"eps":24.23,"bv":118.33,"roe":null,"divYield":94.0,"w52h":1645.0,"w52l":1276.0,"ma50":1359.4,"ma200":1378.71,"beta":0.1,"opm":14.05,"npm":13.31},"ZINKA":{"sym":"ZINKA","name":"BlackBuck Limited","sector":"Technology","ltp":577.1,"change":-9.9,"changePct":-1.687,"open":594.0,"high":595.4,"low":571.35,"prev":587.0,"vol":190068,"avgVol":758933,"mktCap":104843108352,"pe":27.53,"fwdPe":44.48,"pb":8.02,"eps":20.96,"bv":72.0,"roe":null,"divYield":null,"w52h":748.0,"w52l":373.2,"ma50":596.49,"ma200":584.14,"beta":null,"opm":18.17,"npm":63.72}}}