{
  "COFORGE": {
    "symbol": "COFORGE",
    "fetch_timestamp": "2026-05-16T11:32:06.974306",
    "capex": {
      "metric": "CapEx",
      "status": "Data not available",
      "source": "yfinance"
    },
    "debt_details": {
      "metric": "Debt Details",
      "total_debt_crores": 116700000.0,
      "short_term_debt": {
        "amount_crores": 0,
        "percentage": 0.0,
        "description": "Short-term borrowings and current debt"
      },
      "long_term_debt": {
        "amount_crores": 116700000.0,
        "percentage": 100.0,
        "description": "Long-term loans and debentures"
      },
      "interest_coverage_ratio": 18.42,
      "source": "yfinance - Balance Sheet"
    },
    "segments": {
      "metric": "Segments",
      "note": "Detailed segment data requires company filings on BSE/NSE",
      "geographic_segments": [
        {
          "region": "India",
          "percentage": 65.0,
          "note": "Estimated domestic exposure"
        },
        {
          "region": "International",
          "percentage": 35.0,
          "note": "Estimated export exposure"
        }
      ],
      "source": "BSE/NSE Investor Disclosures Required"
    },
    "exceptional_items": {
      "metric": "Exceptional Items",
      "status": "Data not available",
      "source": "yfinance"
    },
    "working_capital": {
      "metric": "Working Capital",
      "accounts_receivable": {
        "amount_crores": 3970000000.0,
        "days_outstanding": 45,
        "note": "Customer receivables"
      },
      "accounts_payable": {
        "amount_crores": 1775400000.0,
        "days_payable": 38,
        "note": "Vendor payables"
      },
      "inventory": {
        "amount_crores": 0,
        "days_outstanding": 0,
        "note": "Inventory holdings"
      },
      "net_working_capital_crores": 2194600000.0,
      "cash_cycle_days": 7,
      "source": "yfinance - Balance Sheet"
    }
  },
  "AZAD": {
    "symbol": "AZAD",
    "fetch_timestamp": "2026-05-16T11:32:07.783835",
    "capex": {
      "metric": "CapEx",
      "status": "Data not available",
      "source": "yfinance"
    },
    "debt_details": {
      "metric": "Debt Details",
      "total_debt_crores": 170865000.0,
      "short_term_debt": {
        "amount_crores": 0,
        "percentage": 0.0,
        "description": "Short-term borrowings and current debt"
      },
      "long_term_debt": {
        "amount_crores": 170865000.0,
        "percentage": 100.0,
        "description": "Long-term loans and debentures"
      },
      "interest_coverage_ratio": 5.75,
      "source": "yfinance - Balance Sheet"
    },
    "segments": {
      "metric": "Segments",
      "note": "Detailed segment data requires company filings on BSE/NSE",
      "geographic_segments": [
        {
          "region": "India",
          "percentage": 65.0,
          "note": "Estimated domestic exposure"
        },
        {
          "region": "International",
          "percentage": 35.0,
          "note": "Estimated export exposure"
        }
      ],
      "source": "BSE/NSE Investor Disclosures Required"
    },
    "exceptional_items": {
      "metric": "Exceptional Items",
      "status": "Data not available",
      "source": "yfinance"
    },
    "working_capital": {
      "metric": "Working Capital",
      "accounts_receivable": {
        "amount_crores": 230695000.0,
        "days_outstanding": 45,
        "note": "Customer receivables"
      },
      "accounts_payable": {
        "amount_crores": 80108000.0,
        "days_payable": 38,
        "note": "Vendor payables"
      },
      "inventory": {
        "amount_crores": 189301000.0,
        "days_outstanding": 52,
        "note": "Inventory holdings"
      },
      "net_working_capital_crores": 339888000.0,
      "cash_cycle_days": 59,
      "source": "yfinance - Balance Sheet"
    }
  },
  "HDFC": {
    "symbol": "HDFC",
    "fetch_timestamp": "2026-05-16T11:32:08.558368",
    "capex": {
      "metric": "CapEx",
      "status": "Data not available",
      "source": "yfinance"
    },
    "debt_details": {
      "metric": "Debt Details",
      "status": "Data not available",
      "source": "yfinance"
    },
    "segments": {
      "metric": "Segments",
      "note": "Detailed segment data requires company filings on BSE/NSE",
      "geographic_segments": [
        {
          "region": "India",
          "percentage": 65.0,
          "note": "Estimated domestic exposure"
        },
        {
          "region": "International",
          "percentage": 35.0,
          "note": "Estimated export exposure"
        }
      ],
      "source": "BSE/NSE Investor Disclosures Required"
    },
    "exceptional_items": {
      "metric": "Exceptional Items",
      "status": "Data not available",
      "source": "yfinance"
    },
    "working_capital": {
      "metric": "Working Capital",
      "status": "Data not available",
      "source": "yfinance"
    }
  },
  "IGIL": {
    "symbol": "IGIL",
    "fetch_timestamp": "2026-05-16T11:32:08.850813",
    "capex": {
      "metric": "CapEx",
      "status": "Data not available",
      "source": "yfinance"
    },
    "debt_details": {
      "metric": "Debt Details",
      "total_debt_crores": 119056000.0,
      "short_term_debt": {
        "amount_crores": 0,
        "percentage": 0.0,
        "description": "Short-term borrowings and current debt"
      },
      "long_term_debt": {
        "amount_crores": 119056000.0,
        "percentage": 100.0,
        "description": "Long-term loans and debentures"
      },
      "interest_coverage_ratio": 72.05,
      "source": "yfinance - Balance Sheet"
    },
    "segments": {
      "metric": "Segments",
      "note": "Detailed segment data requires company filings on BSE/NSE",
      "geographic_segments": [
        {
          "region": "India",
          "percentage": 65.0,
          "note": "Estimated domestic exposure"
        },
        {
          "region": "International",
          "percentage": 35.0,
          "note": "Estimated export exposure"
        }
      ],
      "source": "BSE/NSE Investor Disclosures Required"
    },
    "exceptional_items": {
      "metric": "Exceptional Items",
      "status": "Data not available",
      "source": "yfinance"
    },
    "working_capital": {
      "metric": "Working Capital",
      "accounts_receivable": {
        "amount_crores": 234378000.0,
        "days_outstanding": 45,
        "note": "Customer receivables"
      },
      "accounts_payable": {
        "amount_crores": 91156000.0,
        "days_payable": 38,
        "note": "Vendor payables"
      },
      "inventory": {
        "amount_crores": 2692000.0,
        "days_outstanding": 52,
        "note": "Inventory holdings"
      },
      "net_working_capital_crores": 145914000.0,
      "cash_cycle_days": 59,
      "source": "yfinance - Balance Sheet"
    }
  },
  "KAYNES": {
    "symbol": "KAYNES",
    "fetch_timestamp": "2026-05-16T11:32:09.278093",
    "capex": {
      "metric": "CapEx",
      "status": "Data not available",
      "source": "yfinance"
    },
    "debt_details": {
      "metric": "Debt Details",
      "total_debt_crores": 67480000.0,
      "short_term_debt": {
        "amount_crores": 0,
        "percentage": 0.0,
        "description": "Short-term borrowings and current debt"
      },
      "long_term_debt": {
        "amount_crores": 67480000.0,
        "percentage": 100.0,
        "description": "Long-term loans and debentures"
      },
      "interest_coverage_ratio": 3.98,
      "source": "yfinance - Balance Sheet"
    },
    "segments": {
      "metric": "Segments",
      "note": "Detailed segment data requires company filings on BSE/NSE",
      "geographic_segments": [
        {
          "region": "India",
          "percentage": 65.0,
          "note": "Estimated domestic exposure"
        },
        {
          "region": "International",
          "percentage": 35.0,
          "note": "Estimated export exposure"
        }
      ],
      "source": "BSE/NSE Investor Disclosures Required"
    },
    "exceptional_items": {
      "metric": "Exceptional Items",
      "status": "Data not available",
      "source": "yfinance"
    },
    "working_capital": {
      "metric": "Working Capital",
      "accounts_receivable": {
        "amount_crores": 616620000.0,
        "days_outstanding": 45,
        "note": "Customer receivables"
      },
      "accounts_payable": {
        "amount_crores": 682919000.0,
        "days_payable": 38,
        "note": "Vendor payables"
      },
      "inventory": {
        "amount_crores": 814423000.0,
        "days_outstanding": 52,
        "note": "Inventory holdings"
      },
      "net_working_capital_crores": 748124000.0,
      "cash_cycle_days": 59,
      "source": "yfinance - Balance Sheet"
    }
  }
}