{
  "ABCAPITAL": {
    "ticker": "ABCAPITAL",
    "name": "Aditya Birla Capital Ltd",
    "isin": "INE674K01013",
    "observations": [
      {
        "fetched_at": "2026-05-17T12:18:10.751965+00:00",
        "raw": {
          "data": "fetched"
        }
      }
    ]
  },
  "ABFRL": {
    "ticker": "ABFRL",
    "name": "Aditya Birla Fashion & Retail Ltd",
    "isin": "INE647O01011",
    "observations": [
      {
        "fetched_at": "2026-05-17T12:18:13.147064+00:00",
        "raw": {
          "data": "fetched"
        }
      }
    ]
  },
  "ACMESOLAR": {
    "ticker": "ACMESOLAR",
    "name": "ACME SOLAR HOLDINGS LTD",
    "isin": "INE622W01025",
    "observations": [
      {
        "fetched_at": "2026-05-17T12:18:15.302708+00:00",
        "raw": {
          "data": "fetched"
        }
      }
    ]
  },
  "AFCONS": {
    "ticker": "AFCONS",
    "name": "AFCONS INFRASTRUCTURE LTD",
    "isin": "INE101I01011",
    "observations": [
      {
        "fetched_at": "2026-05-17T12:18:17.497824+00:00",
        "raw": {
          "data": "fetched"
        }
      }
    ]
  },
  "APOLLOHOSP": {
    "ticker": "APOLLOHOSP",
    "name": "Apollo Hospitals Enterprise Ltd",
    "isin": "INE437A01024",
    "observations": [
      {
        "fetched_at": "2026-05-17T12:18:19.790734+00:00",
        "raw": {
          "data": "fetched"
        }
      }
    ]
  },
  "ARE&M": {
    "ticker": "ARE&M",
    "name": "AMARA RAJA ENERGY MOB LTD",
    "isin": "INE885A01032",
    "observations": [
      {
        "fetched_at": "2026-05-17T12:18:21.986666+00:00",
        "raw": {
          "data": "fetched"
        }
      }
    ]
  },
  "ARROWGREEN": {
    "ticker": "ARROWGREEN",
    "name": "Arrow Greentech Ltd",
    "isin": "INE570A01022",
    "observations": [
      {
        "fetched_at": "2026-05-17T12:18:24.195323+00:00",
        "raw": {
          "data": "fetched"
        }
      }
    ]
  },
  "ASALCBR": {
    "ticker": "ASALCBR",
    "name": "Associated Alcohols & Breweries Ltd",
    "isin": "INE073G01016",
    "observations": [
      {
        "fetched_at": "2026-05-17T12:18:26.422426+00:00",
        "raw": {
          "data": "fetched"
        }
      }
    ]
  },
  "ASHOKA": {
    "ticker": "ASHOKA",
    "name": "Ashoka Buildcon Ltd",
    "isin": "INE442H01029",
    "observations": [
      {
        "fetched_at": "2026-05-17T12:18:28.542937+00:00",
        "raw": {
          "data": "fetched"
        }
      }
    ]
  },
  "AVANTIFEED": {
    "ticker": "AVANTIFEED",
    "name": "Avanti Feeds Ltd",
    "isin": "INE871C01038",
    "observations": [
      {
        "fetched_at": "2026-05-17T12:18:30.742949+00:00",
        "raw": {
          "data": "fetched"
        }
      }
    ]
  },
  "AZAD": {
    "ticker": "AZAD",
    "name": "AZAD ENGINEERING LIMITED",
    "isin": "INE02IJ01035",
    "observations": [
      {
        "fetched_at": "2026-05-17T12:18:32.959416+00:00",
        "raw": {
          "data": "fetched"
        }
      }
    ]
  },
  "AZADIND": {
    "ticker": "AZADIND",
    "name": "AZAD INDIA MOBILITY LIMITED",
    "isin": "INE566M01017",
    "observations": [
      {
        "fetched_at": "2026-05-17T12:18:35.432334+00:00",
        "raw": {
          "error": "Not found"
        }
      }
    ]
  },
  "BDL": {
    "ticker": "BDL",
    "name": "Bharat Dynamics Ltd",
    "isin": "INE171Z01018",
    "observations": [
      {
        "fetched_at": "2026-05-17T12:18:37.603301+00:00",
        "raw": {
          "data": "fetched"
        }
      }
    ]
  },
  "BIOCON": {
    "ticker": "BIOCON",
    "name": "Biocon Ltd",
    "isin": "INE376G01013",
    "observations": [
      {
        "fetched_at": "2026-05-17T12:18:39.851851+00:00",
        "raw": {
          "data": "fetched"
        }
      }
    ]
  },
  "BLACKBOX": {
    "ticker": "BLACKBOX",
    "name": "BLACK BOX LIMITED",
    "isin": "INE676A01027",
    "observations": [
      {
        "fetched_at": "2026-05-17T12:18:42.170686+00:00",
        "raw": {
          "error": "Not found"
        }
      }
    ]
  },
  "CAPITALNUM": {
    "ticker": "CAPITALNUM",
    "name": "CAPITALNUMBERS INFOTECH  LIMIT",
    "isin": "INE0S0N01014",
    "observations": [
      {
        "fetched_at": "2026-05-17T12:18:44.377608+00:00",
        "raw": {
          "error": "Not found"
        }
      }
    ]
  },
  "CDSL": {
    "ticker": "CDSL",
    "name": "Central Depository Services (India) Ltd",
    "isin": "INE736A01011",
    "observations": [
      {
        "fetched_at": "2026-05-17T12:18:46.621655+00:00",
        "raw": {
          "data": "fetched"
        }
      }
    ]
  },
  "CELLO": {
    "ticker": "CELLO",
    "name": "CELLO WORLD LIMITED",
    "isin": "INE0LMW01024",
    "observations": [
      {
        "fetched_at": "2026-05-17T12:18:48.867626+00:00",
        "raw": {
          "data": "fetched"
        }
      }
    ]
  },
  "CIGNITITEC": {
    "ticker": "CIGNITITEC",
    "name": "Cigniti Technologies Ltd",
    "isin": "INE675C01017",
    "observations": [
      {
        "fetched_at": "2026-05-17T12:18:51.009431+00:00",
        "raw": {
          "data": "fetched"
        }
      }
    ]
  },
  "COCHINSHIP": {
    "ticker": "COCHINSHIP",
    "name": "Cochin Shipyard Ltd",
    "isin": "INE704P01025",
    "observations": [
      {
        "fetched_at": "2026-05-17T12:18:53.185186+00:00",
        "raw": {
          "data": "fetched"
        }
      }
    ]
  },
  "COFORGE": {
    "ticker": "COFORGE",
    "name": "Coforge Ltd",
    "isin": "INE591G01017",
    "observations": [
      {
        "fetched_at": "2026-05-17T12:18:55.465196+00:00",
        "raw": {
          "data": "fetched"
        }
      }
    ]
  },
  "DATAMATICS": {
    "ticker": "DATAMATICS",
    "name": "Datamatics Global Services Ltd",
    "isin": "INE771C01014",
    "observations": [
      {
        "fetched_at": "2026-05-17T12:18:57.867564+00:00",
        "raw": {
          "data": "fetched"
        }
      }
    ]
  },
  "DATAPATTNS": {
    "ticker": "DATAPATTNS",
    "name": "Data Patterns (India) Limited",
    "isin": "INE0IX101010",
    "observations": [
      {
        "fetched_at": "2026-05-17T12:19:00.015787+00:00",
        "raw": {
          "data": "fetched"
        }
      }
    ]
  },
  "DRREDDY": {
    "ticker": "DRREDDY",
    "name": "Dr Reddys Laboratories Ltd",
    "isin": "INE089A01023",
    "observations": [
      {
        "fetched_at": "2026-05-17T12:19:02.226380+00:00",
        "raw": {
          "data": "fetched"
        }
      }
    ]
  },
  "ENGINERSIN": {
    "ticker": "ENGINERSIN",
    "name": "Engineers India Ltd",
    "isin": "INE510A01028",
    "observations": [
      {
        "fetched_at": "2026-05-17T12:19:04.564773+00:00",
        "raw": {
          "data": "fetched"
        }
      }
    ]
  },
  "FINCABLES": {
    "ticker": "FINCABLES",
    "name": "Finolex Cables Ltd",
    "isin": "INE235A01022",
    "observations": [
      {
        "fetched_at": "2026-05-17T12:19:06.747352+00:00",
        "raw": {
          "data": "fetched"
        }
      }
    ]
  },
  "GESHIP": {
    "ticker": "GESHIP",
    "name": "Great Eastern Shipping Company Ltd",
    "isin": "INE017A01032",
    "observations": [
      {
        "fetched_at": "2026-05-17T12:19:08.942894+00:00",
        "raw": {
          "data": "fetched"
        }
      }
    ]
  },
  "GRSE": {
    "ticker": "GRSE",
    "name": "Garden Reach Shipbuilders & Engineers Ltd",
    "isin": "INE382Z01011",
    "observations": [
      {
        "fetched_at": "2026-05-17T12:19:11.187509+00:00",
        "raw": {
          "data": "fetched"
        }
      }
    ]
  },
  "HAL": {
    "ticker": "HAL",
    "name": "Hindustan Aeronautics Ltd",
    "isin": "INE066F01020",
    "observations": [
      {
        "fetched_at": "2026-05-17T12:19:13.361990+00:00",
        "raw": {
          "data": "fetched"
        }
      }
    ]
  },
  "HBLENGINE": {
    "ticker": "HBLENGINE",
    "name": "HBL ENGINEERING LTD",
    "isin": "INE292B01021",
    "observations": [
      {
        "fetched_at": "2026-05-17T12:19:15.495867+00:00",
        "raw": {
          "data": "fetched"
        }
      }
    ]
  },
  "HCLTECH": {
    "ticker": "HCLTECH",
    "name": "HCl ltd",
    "isin": "INE860A01027",
    "observations": [
      {
        "fetched_at": "2026-05-17T12:19:17.712387+00:00",
        "raw": {
          "data": "fetched"
        }
      }
    ]
  },
  "HDFCBANK": {
    "ticker": "HDFCBANK",
    "name": "HDFC Bank Ltd",
    "isin": "INE040A01034",
    "observations": [
      {
        "fetched_at": "2026-05-17T12:19:20.082601+00:00",
        "raw": {
          "data": "fetched"
        }
      }
    ]
  },
  "HDFCLIFE": {
    "ticker": "HDFCLIFE",
    "name": "HDFC Life Insurance Company Ltd",
    "isin": "INE795G01014",
    "observations": [
      {
        "fetched_at": "2026-05-17T12:19:22.293304+00:00",
        "raw": {
          "data": "fetched"
        }
      }
    ]
  },
  "HEBL": {
    "ticker": "HEBL",
    "name": "HIGH ENERGY BATTERIES (INDIA)",
    "isin": "INE783A01021",
    "observations": [
      {
        "fetched_at": "2026-05-17T12:19:24.460275+00:00",
        "raw": {
          "error": "Not found"
        }
      }
    ]
  },
  "HINDCOPPER": {
    "ticker": "HINDCOPPER",
    "name": "Hindustan Copper Ltd",
    "isin": "INE531E01026",
    "observations": [
      {
        "fetched_at": "2026-05-17T12:19:26.590166+00:00",
        "raw": {
          "data": "fetched"
        }
      }
    ]
  },
  "HINDZINC": {
    "ticker": "HINDZINC",
    "name": "Hindustan Zinc Ltd",
    "isin": "INE267A01025",
    "observations": [
      {
        "fetched_at": "2026-05-17T12:19:28.861057+00:00",
        "raw": {
          "data": "fetched"
        }
      }
    ]
  },
  "HIRECT": {
    "ticker": "HIRECT",
    "name": "Hind Rectifiers Ltd",
    "isin": "INE835D01023",
    "observations": [
      {
        "fetched_at": "2026-05-17T12:19:31.180973+00:00",
        "raw": {
          "data": "fetched"
        }
      }
    ]
  },
  "ICICIBANK": {
    "ticker": "ICICIBANK",
    "name": "ICICI Bank Ltd",
    "isin": "INE090A01021",
    "observations": [
      {
        "fetched_at": "2026-05-17T12:19:33.406506+00:00",
        "raw": {
          "data": "fetched"
        }
      }
    ]
  },
  "IDEAFORGE": {
    "ticker": "IDEAFORGE",
    "name": "IDEAFORGE TECHNO LTD",
    "isin": "INE349Y01013",
    "observations": [
      {
        "fetched_at": "2026-05-17T12:19:35.563702+00:00",
        "raw": {
          "data": "fetched"
        }
      }
    ]
  },
  "IDFCFIRSTB": {
    "ticker": "IDFCFIRSTB",
    "name": "IDFC First Bank Ltd",
    "isin": "INE092T01019",
    "observations": [
      {
        "fetched_at": "2026-05-17T12:19:37.919836+00:00",
        "raw": {
          "data": "fetched"
        }
      }
    ]
  },
  "IGIL": {
    "ticker": "IGIL",
    "name": "INTERNATIO GEMM INS (I) L",
    "isin": "INE0QXT01018",
    "observations": [
      {
        "fetched_at": "2026-05-17T12:19:40.093673+00:00",
        "raw": {
          "data": "fetched"
        }
      }
    ]
  },
  "INDIANB": {
    "ticker": "INDIANB",
    "name": "Indian Bank",
    "isin": "INE562A01011",
    "observations": [
      {
        "fetched_at": "2026-05-17T12:19:42.349506+00:00",
        "raw": {
          "data": "fetched"
        }
      }
    ]
  },
  "INDOTECH": {
    "ticker": "INDOTECH",
    "name": "Indo Tech Transformers Ltd",
    "isin": "INE332H01014",
    "observations": [
      {
        "fetched_at": "2026-05-17T12:19:44.569192+00:00",
        "raw": {
          "data": "fetched"
        }
      }
    ]
  },
  "INDUSTOWER": {
    "ticker": "INDUSTOWER",
    "name": "INDUS TOWERS LIMITED",
    "isin": "INE121J01017",
    "observations": [
      {
        "fetched_at": "2026-05-17T12:19:46.842740+00:00",
        "raw": {
          "data": "fetched"
        }
      }
    ]
  },
  "INFY": {
    "ticker": "INFY",
    "name": "Infosys Ltd",
    "isin": "INE009A01021",
    "observations": [
      {
        "fetched_at": "2026-05-17T12:19:49.062743+00:00",
        "raw": {
          "data": "fetched"
        }
      }
    ]
  },
  "INOXINDIA": {
    "ticker": "INOXINDIA",
    "name": "INOX INDIA LIMITED",
    "isin": "INE0HPK01020",
    "observations": [
      {
        "fetched_at": "2026-05-17T12:19:51.289515+00:00",
        "raw": {
          "data": "fetched"
        }
      }
    ]
  },
  "INTERARCH": {
    "ticker": "INTERARCH",
    "name": "INTERARCH BUILDING PROD L",
    "isin": "INE00M901018",
    "observations": [
      {
        "fetched_at": "2026-05-17T12:19:53.484529+00:00",
        "raw": {
          "data": "fetched"
        }
      }
    ]
  },
  "IOC": {
    "ticker": "IOC",
    "name": "Indian Oil Corporation Ltd",
    "isin": "INE242A01010",
    "observations": [
      {
        "fetched_at": "2026-05-17T12:19:55.728563+00:00",
        "raw": {
          "data": "fetched"
        }
      }
    ]
  },
  "ITC": {
    "ticker": "ITC",
    "name": "ITC Ltd",
    "isin": "INE154A01025",
    "observations": [
      {
        "fetched_at": "2026-05-17T12:19:58.086509+00:00",
        "raw": {
          "data": "fetched"
        }
      }
    ]
  },
  "JUNIORBEES": {
    "ticker": "JUNIORBEES",
    "name": "SBI ETF Nifty Next 50",
    "isin": "INF200KA1FS3",
    "observations": [
      {
        "fetched_at": "2026-05-17T12:19:59.994529+00:00",
        "raw": {
          "data": "fetched"
        }
      }
    ]
  },
  "JYOTHYLAB": {
    "ticker": "JYOTHYLAB",
    "name": "Jyothy Labs Ltd",
    "isin": "INE668F01031",
    "observations": [
      {
        "fetched_at": "2026-05-17T12:20:02.147039+00:00",
        "raw": {
          "data": "fetched"
        }
      }
    ]
  },
  "KAYNES": {
    "ticker": "KAYNES",
    "name": "KAYNES TECHNOLOGY IND LTD",
    "isin": "INE918Z01012",
    "observations": [
      {
        "fetched_at": "2026-05-17T12:20:04.324608+00:00",
        "raw": {
          "data": "fetched"
        }
      }
    ]
  },
  "KEI": {
    "ticker": "KEI",
    "name": "KEI Industries Ltd",
    "isin": "INE878B01027",
    "observations": [
      {
        "fetched_at": "2026-05-17T12:20:06.593392+00:00",
        "raw": {
          "data": "fetched"
        }
      }
    ]
  },
  "KPENERGY": {
    "ticker": "KPENERGY",
    "name": "K.P. Energy Ltd",
    "isin": "INE542W01017",
    "observations": [
      {
        "fetched_at": "2026-05-17T12:20:08.819525+00:00",
        "raw": {
          "error": "Not found"
        }
      }
    ]
  },
  "KPPL": {
    "ticker": "KPPL",
    "name": "Kwality Pharmaceuticals Ltd",
    "isin": "INE552U01010",
    "observations": [
      {
        "fetched_at": "2026-05-17T12:20:10.940359+00:00",
        "raw": {
          "error": "Not found"
        }
      }
    ]
  },
  "MAHABANK": {
    "ticker": "MAHABANK",
    "name": "Bank of Maharashtra",
    "isin": "INE457A01014",
    "observations": [
      {
        "fetched_at": "2026-05-17T12:20:13.125675+00:00",
        "raw": {
          "data": "fetched"
        }
      }
    ]
  },
  "MAITHANALL": {
    "ticker": "MAITHANALL",
    "name": "Maithan Alloys Ltd",
    "isin": "INE683C01011",
    "observations": [
      {
        "fetched_at": "2026-05-17T12:20:15.392696+00:00",
        "raw": {
          "data": "fetched"
        }
      }
    ]
  },
  "MAPMYINDIA": {
    "ticker": "MAPMYINDIA",
    "name": "C.E. Info Systems Limited",
    "isin": "INE0BV301023",
    "observations": [
      {
        "fetched_at": "2026-05-17T12:20:17.605186+00:00",
        "raw": {
          "data": "fetched"
        }
      }
    ]
  },
  "MARKSANS": {
    "ticker": "MARKSANS",
    "name": "Marksans Pharma Ltd",
    "isin": "INE750C01026",
    "observations": [
      {
        "fetched_at": "2026-05-17T12:20:19.796715+00:00",
        "raw": {
          "data": "fetched"
        }
      }
    ]
  },
  "MBEL": {
    "ticker": "MBEL",
    "name": "M AND B ENGINEERING LTD",
    "isin": "INE0Q9N01012",
    "observations": [
      {
        "fetched_at": "2026-05-17T12:20:22.135395+00:00",
        "raw": {
          "data": "fetched"
        }
      }
    ]
  },
  "MCDOWELL-N": {
    "ticker": "MCDOWELL-N",
    "name": "United Spirits Ltd",
    "isin": "INE854D01024",
    "observations": [
      {
        "fetched_at": "2026-05-17T12:20:24.207682+00:00",
        "raw": {
          "error": "Not found"
        }
      }
    ]
  },
  "NCC": {
    "ticker": "NCC",
    "name": "NCC Ltd",
    "isin": "INE868B01028",
    "observations": [
      {
        "fetched_at": "2026-05-17T12:20:26.512683+00:00",
        "raw": {
          "data": "fetched"
        }
      }
    ]
  },
  "NETWEB": {
    "ticker": "NETWEB",
    "name": "NETWEB TECH INDIA LTD",
    "isin": "INE0NT901020",
    "observations": [
      {
        "fetched_at": "2026-05-17T12:20:28.855493+00:00",
        "raw": {
          "data": "fetched"
        }
      }
    ]
  },
  "NIFTYBEES": {
    "ticker": "NIFTYBEES",
    "name": "SBI ETF Nifty 50",
    "isin": "INF200KA1FS1",
    "observations": [
      {
        "fetched_at": "2026-05-17T12:20:30.828178+00:00",
        "raw": {
          "data": "fetched"
        }
      }
    ]
  },
  "OIL": {
    "ticker": "OIL",
    "name": "Oil India Ltd",
    "isin": "INE274J01014",
    "observations": [
      {
        "fetched_at": "2026-05-17T12:20:32.935291+00:00",
        "raw": {
          "data": "fetched"
        }
      }
    ]
  },
  "PFC": {
    "ticker": "PFC",
    "name": "Power Finance Corporation Ltd",
    "isin": "INE134E01011",
    "observations": [
      {
        "fetched_at": "2026-05-17T12:20:35.234265+00:00",
        "raw": {
          "data": "fetched"
        }
      }
    ]
  },
  "POWERGRID": {
    "ticker": "POWERGRID",
    "name": "Power Grid Corporation of India Ltd",
    "isin": "INE752E01010",
    "observations": [
      {
        "fetched_at": "2026-05-17T12:20:37.516890+00:00",
        "raw": {
          "data": "fetched"
        }
      }
    ]
  },
  "PVRINOX": {
    "ticker": "PVRINOX",
    "name": "PVR Ltd",
    "isin": "INE191H01014",
    "observations": [
      {
        "fetched_at": "2026-05-17T12:20:39.768862+00:00",
        "raw": {
          "data": "fetched"
        }
      }
    ]
  },
  "QUALITY": {
    "ticker": "QUALITY",
    "name": "QUALITY POWER ELEC EQUP L",
    "isin": "INE0Q8G01014",
    "observations": [
      {
        "fetched_at": "2026-05-17T12:20:41.848374+00:00",
        "raw": {
          "error": "Not found"
        }
      }
    ]
  },
  "RATEGAIN": {
    "ticker": "RATEGAIN",
    "name": "Rategain Travel Technologies Limited",
    "isin": "INE0CLI01024",
    "observations": [
      {
        "fetched_at": "2026-05-17T12:20:44.008330+00:00",
        "raw": {
          "data": "fetched"
        }
      }
    ]
  },
  "RECLTD": {
    "ticker": "RECLTD",
    "name": "REC Ltd",
    "isin": "INE020B01018",
    "observations": [
      {
        "fetched_at": "2026-05-17T12:20:46.411386+00:00",
        "raw": {
          "data": "fetched"
        }
      }
    ]
  },
  "REDTAPE": {
    "ticker": "REDTAPE",
    "name": "REDTAPE LIMITED",
    "isin": "INE0L9R01012",
    "observations": [
      {
        "fetched_at": "2026-05-17T12:20:48.577357+00:00",
        "raw": {
          "data": "fetched"
        }
      }
    ]
  },
  "REPCOHOME": {
    "ticker": "REPCOHOME",
    "name": "Repco Home Finance Ltd",
    "isin": "INE612J01015",
    "observations": [
      {
        "fetched_at": "2026-05-17T12:20:50.759334+00:00",
        "raw": {
          "data": "fetched"
        }
      }
    ]
  },
  "REVATHI": {
    "ticker": "REVATHI",
    "name": "REVATHI EQUIPMENT INDIA L",
    "isin": "INE617A01013",
    "observations": [
      {
        "fetched_at": "2026-05-17T12:20:52.994662+00:00",
        "raw": {
          "error": "Not found"
        }
      }
    ]
  },
  "ROSSTECH": {
    "ticker": "ROSSTECH",
    "name": "ROSSELL TECHSYS LIMITED",
    "isin": "INE847C01020",
    "observations": [
      {
        "fetched_at": "2026-05-17T12:20:55.259264+00:00",
        "raw": {
          "data": "fetched"
        }
      }
    ]
  },
  "S&SPOWER": {
    "ticker": "S&SPOWER",
    "name": "S & S Power Switchgear Ltd",
    "isin": "INE902B01017",
    "observations": [
      {
        "fetched_at": "2026-05-17T12:20:57.421050+00:00",
        "raw": {
          "data": "fetched"
        }
      }
    ]
  },
  "SAGILITY": {
    "ticker": "SAGILITY",
    "name": "SAGILITY INDIA LIMITED",
    "isin": "INE0W2G01015",
    "observations": [
      {
        "fetched_at": "2026-05-17T12:20:59.597576+00:00",
        "raw": {
          "data": "fetched"
        }
      }
    ]
  },
  "SANDUMA": {
    "ticker": "SANDUMA",
    "name": "Sandur Manganese & Iron Ores Ltd",
    "isin": "INE149K01016",
    "observations": [
      {
        "fetched_at": "2026-05-17T12:21:01.914722+00:00",
        "raw": {
          "data": "fetched"
        }
      }
    ]
  },
  "SBIN": {
    "ticker": "SBIN",
    "name": "State Bank of India",
    "isin": "INE062A01020",
    "observations": [
      {
        "fetched_at": "2026-05-17T12:21:04.121616+00:00",
        "raw": {
          "data": "fetched"
        }
      }
    ]
  },
  "SHILCHAR": {
    "ticker": "SHILCHAR",
    "name": "Shilchar Technologies Ltd",
    "isin": "INE024F01011",
    "observations": [
      {
        "fetched_at": "2026-05-17T12:21:06.276608+00:00",
        "raw": {
          "error": "Not found"
        }
      }
    ]
  },
  "SHREEREF": {
    "ticker": "SHREEREF",
    "name": "SHREE REFRIGERATIONS LIMITED",
    "isin": "INE0QZ601016",
    "observations": [
      {
        "fetched_at": "2026-05-17T12:21:08.571238+00:00",
        "raw": {
          "error": "Not found"
        }
      }
    ]
  },
  "SIKA": {
    "ticker": "SIKA",
    "name": "Sika Interplant Systems Ltd",
    "isin": "INE438E01010",
    "observations": [
      {
        "fetched_at": "2026-05-17T12:21:10.825387+00:00",
        "raw": {
          "data": "fetched"
        }
      }
    ]
  },
  "SKMEGGPROD": {
    "ticker": "SKMEGGPROD",
    "name": "SKM Egg Products Export (India) Ltd",
    "isin": "INE411D01015",
    "observations": [
      {
        "fetched_at": "2026-05-17T12:21:12.963432+00:00",
        "raw": {
          "data": "fetched"
        }
      }
    ]
  },
  "SUNFLAG": {
    "ticker": "SUNFLAG",
    "name": "Sunflag Iron & Steel Company Ltd",
    "isin": "INE947A01014",
    "observations": [
      {
        "fetched_at": "2026-05-17T12:21:15.272686+00:00",
        "raw": {
          "data": "fetched"
        }
      }
    ]
  },
  "SUPRIYA": {
    "ticker": "SUPRIYA",
    "name": "Supriya Lifescience Limited",
    "isin": "INE07RO01027",
    "observations": [
      {
        "fetched_at": "2026-05-17T12:21:17.533803+00:00",
        "raw": {
          "data": "fetched"
        }
      }
    ]
  },
  "SUYOG": {
    "ticker": "SUYOG",
    "name": "Suyog Telematics Ltd",
    "isin": "INE442P01014",
    "observations": [
      {
        "fetched_at": "2026-05-17T12:21:19.814356+00:00",
        "raw": {
          "data": "fetched"
        }
      }
    ]
  },
  "SUZLON": {
    "ticker": "SUZLON",
    "name": "SUZLON ENERGY LIMITED",
    "isin": "INE040H01021",
    "observations": [
      {
        "fetched_at": "2026-05-17T12:21:21.998031+00:00",
        "raw": {
          "data": "fetched"
        }
      }
    ]
  },
  "TATAPOWER": {
    "ticker": "TATAPOWER",
    "name": "Tata Power Company Ltd",
    "isin": "INE245A01021",
    "observations": [
      {
        "fetched_at": "2026-05-17T12:21:24.233881+00:00",
        "raw": {
          "data": "fetched"
        }
      }
    ]
  },
  "TDPOWERSYS": {
    "ticker": "TDPOWERSYS",
    "name": "TD Power Systems Ltd",
    "isin": "INE419M01027",
    "observations": [
      {
        "fetched_at": "2026-05-17T12:21:26.540952+00:00",
        "raw": {
          "data": "fetched"
        }
      }
    ]
  },
  "TITANBIO": {
    "ticker": "TITANBIO",
    "name": "Titan Biotech Ltd",
    "isin": "INE150C01011",
    "observations": [
      {
        "fetched_at": "2026-05-17T12:21:28.663383+00:00",
        "raw": {
          "error": "Not found"
        }
      }
    ]
  },
  "TRUALT": {
    "ticker": "TRUALT",
    "name": "TRUALT BIOENERGY LIMITED",
    "isin": "INE0MWH01014",
    "observations": [
      {
        "fetched_at": "2026-05-17T12:21:30.950472+00:00",
        "raw": {
          "data": "fetched"
        }
      }
    ]
  },
  "VEDL": {
    "ticker": "VEDL",
    "name": "Vedanta Ltd",
    "isin": "INE205A01025",
    "observations": [
      {
        "fetched_at": "2026-05-17T12:21:33.232177+00:00",
        "raw": {
          "data": "fetched"
        }
      }
    ]
  },
  "VENTIVE": {
    "ticker": "VENTIVE",
    "name": "VENTIVE HOSPITALITY LTD",
    "isin": "INE0SBH01019",
    "observations": [
      {
        "fetched_at": "2026-05-17T12:21:35.610327+00:00",
        "raw": {
          "data": "fetched"
        }
      }
    ]
  },
  "VOLTAMP": {
    "ticker": "VOLTAMP",
    "name": "Voltamp Transformers Ltd",
    "isin": "INE540H01012",
    "observations": [
      {
        "fetched_at": "2026-05-17T12:21:37.868642+00:00",
        "raw": {
          "data": "fetched"
        }
      }
    ]
  },
  "WAAREEENER": {
    "ticker": "WAAREEENER",
    "name": "Waaree energies Ltd",
    "isin": "INE0MGR01012",
    "observations": [
      {
        "fetched_at": "2026-05-17T12:21:40.168819+00:00",
        "raw": {
          "data": "fetched"
        }
      }
    ]
  },
  "ZENTEC": {
    "ticker": "ZENTEC",
    "name": "Zen Technologies Ltd",
    "isin": "INE251B01027",
    "observations": [
      {
        "fetched_at": "2026-05-17T12:21:42.476453+00:00",
        "raw": {
          "data": "fetched"
        }
      }
    ]
  },
  "ZINKA": {
    "ticker": "ZINKA",
    "name": "ZINKA LOGISTICS SOL LTD",
    "isin": "INE0UI401011",
    "observations": [
      {
        "fetched_at": "2026-05-17T12:21:44.658829+00:00",
        "raw": {
          "error": "Not found"
        }
      }
    ]
  }
}