{
  "updated": "2026-07-01T08:41:32.560201+00:00",
  "sectors": {
    "Information Technology": {
      "symbol": "^CNXIT",
      "name": "Nifty IT",
      "price": 25880.8,
      "change_52w_pct": -33.92,
      "change_1d_pct": -1.59,
      "as_of": "2026-06-29"
    },
    "Financials": {
      "symbol": "^NSEBANK",
      "name": "Nifty Bank",
      "price": 58017.45,
      "change_52w_pct": 1.73,
      "change_1d_pct": 0.82,
      "as_of": "2026-06-29"
    },
    "Healthcare": {
      "symbol": "^CNXPHARMA",
      "name": "Nifty Pharma",
      "price": 25218.9,
      "change_52w_pct": 12.66,
      "change_1d_pct": -0.42,
      "as_of": "2026-06-29"
    },
    "Consumer Staples": {
      "symbol": "^CNXFMCG",
      "name": "Nifty FMCG",
      "price": 49839.0,
      "change_52w_pct": -8.95,
      "change_1d_pct": 0.85,
      "as_of": "2026-06-29"
    },
    "Consumer Discretionary": {
      "symbol": "^CNXAUTO",
      "name": "Nifty Auto",
      "price": 26786.85,
      "change_52w_pct": 11.7,
      "change_1d_pct": -0.71,
      "as_of": "2026-06-29"
    },
    "Materials": {
      "symbol": "^CNXMETAL",
      "name": "Nifty Metal",
      "price": 12402.5,
      "change_52w_pct": 29.46,
      "change_1d_pct": -0.35,
      "as_of": "2026-06-29"
    },
    "Energy": {
      "symbol": "^CNXENERGY",
      "name": "Nifty Energy",
      "price": 39712.55,
      "change_52w_pct": 8.77,
      "change_1d_pct": 0.19,
      "as_of": "2026-06-29"
    },
    "Industrials": {
      "symbol": "^CNXINFRA",
      "name": "Nifty Infra",
      "price": 9450.55,
      "change_52w_pct": 0.18,
      "change_1d_pct": -0.11,
      "as_of": "2026-06-29"
    },
    "Utilities": {
      "symbol": "^CNXPSE",
      "name": "Nifty PSE",
      "price": 10008.0,
      "change_52w_pct": -1.0,
      "change_1d_pct": 0.54,
      "as_of": "2026-06-29"
    },
    "Defence": {
      "symbol": "MODEFENCE.NS",
      "name": "Nifty India Defence",
      "price": 104.79,
      "change_52w_pct": 7.03,
      "change_1d_pct": 0.11,
      "as_of": "2026-06-29"
    },
    "Telecom": {
      "symbol": "^CNXPSE",
      "name": "Nifty PSE",
      "price": 10008.0,
      "change_52w_pct": -1.0,
      "change_1d_pct": 0.54,
      "as_of": "2026-06-29"
    },
    "ETF": {
      "symbol": "^NSEI",
      "name": "Nifty 50",
      "price": 24037.7,
      "change_52w_pct": -5.59,
      "change_1d_pct": 0.72,
      "as_of": "2026-06-29"
    }
  }
}